README.md
pyproject.toml
toxicpoller/__init__.py
toxicpoller/cmds.py
toxicpoller/poller.py
toxicpoller/server.py
toxicpoller.egg-info/PKG-INFO
toxicpoller.egg-info/SOURCES.txt
toxicpoller.egg-info/dependency_links.txt
toxicpoller.egg-info/entry_points.txt
toxicpoller.egg-info/requires.txt
toxicpoller.egg-info/top_level.txt